litebox/__init__.py
litebox/constants.py
litebox/exceptions.py
litebox/globals.py
litebox/main.py
litebox/utils.py
litebox-0.2.0.dist-info/LICENSE
litebox-0.2.0.dist-info/WHEEL
litebox-0.2.0.dist-info/METADATA
litebox-0.2.0.dist-info/RECORD
