Metadata-Version: 2.1
Name: litebox
Version: 0.2.0
Summary: 
Home-page: https://github.com/manimino/litebox/
Author: Theo Walker
Author-email: theo.ca.walker@gmail.com
Requires-Python: >=3.7,<4.0
Classifier: Programming Language :: Python :: 3
Classifier: Programming Language :: Python :: 3.10
Classifier: Programming Language :: Python :: 3.7
Classifier: Programming Language :: Python :: 3.8
Classifier: Programming Language :: Python :: 3.9
Project-URL: Documentation, https://pypi.org/project/litebox/
Project-URL: Repository, https://github.com/manimino/litebox/
